LICENSE
README.md
setup.py
zhatlebaye_kafka/__init__.py
zhatlebaye_kafka/consumer.py
zhatlebaye_kafka/producer.py
zhatlebaye_kafka/router.py
zhatlebaye_kafka.egg-info/PKG-INFO
zhatlebaye_kafka.egg-info/SOURCES.txt
zhatlebaye_kafka.egg-info/dependency_links.txt
zhatlebaye_kafka.egg-info/requires.txt
zhatlebaye_kafka.egg-info/top_level.txt