Metadata-Version: 2.1
Name: zhatlebaye-kafka
Version: 0.1.6
Summary: An extension to the aiokafka library with enhanced producer and consumer functionalities
Home-page: https://gitlab.com/di-halyk-academy-zhatlebaye/zhatlebaye-kafka
Author: Yerlan Yesmoldin
Author-email: e_esmoldin@kbtu.kz
Classifier: License :: OSI Approved :: MIT License
Classifier: Programming Language :: Python :: 3.10
Requires-Python: >=3.10
License-File: LICENSE
